{"content":[{"id":"7e52eaa2","settings":{"layout":"full_width","gap":"no","padding":{"unit":"px","top":"0","right":"0","bottom":"0","left":"0","isLinked":true}},"elements":[{"id":"4c0202b8","settings":{"_column_size":100,"_inline_size":null,"content_position":"top","space_between_widgets":0,"background_color":"#FFFFFF","box_shadow_box_shadow_type":"yes","box_shadow_box_shadow":{"horizontal":0,"vertical":0,"blur":18,"spread":0,"color":"rgba(0, 0, 0, 0.04)"},"margin":{"unit":"px","top":"0","right":"0","bottom":"0","left":"0","isLinked":true},"background_background":"classic"},"elements":[{"id":"4abde5ee","settings":{"layout":"full_width","gap":"no"},"elements":[{"id":"669be3f5","settings":{"_column_size":100,"_inline_size":null,"space_between_widgets":0,"content_position":"top","background_color":"#FFFFFF","box_shadow_box_shadow":{"horizontal":0,"vertical":0,"blur":18,"spread":0,"color":"rgba(0, 0, 0, 0.31)"}},"elements":[{"id":"a92bb59","settings":{"__dynamic__":{"image":"[elementor-tag id=\"\" name=\"post-featured-image\" settings=\"%7B%22fallback%22%3A%7B%22url%22%3A%22%22%2C%22id%22%3A%22%22%2C%22size%22%3A%22%22%7D%7D\"]"},"image_size":"custom","image_custom_dimension":{"width":"800","height":"600"},"align":"center"},"elements":[],"isInner":false,"widgetType":"theme-post-featured-image","elType":"widget"},{"id":"33a0be60","settings":{"icon_list":[{"selected_icon":{"value":{"url":"https:\/\/blocks.elementorking.com\/wp-content\/uploads\/2023\/12\/blog-icon-list-1.svg","id":22547},"library":"svg"},"_id":"9a1fe63","custom_date_format":"F j, Y","custom_time_format":"g:i a","show_icon":"custom","link":"","type":"author"},{"selected_icon":{"value":{"url":"https:\/\/blocks.elementorking.com\/wp-content\/uploads\/2023\/12\/blog-icon-list-6.svg","id":22552},"library":"svg"},"custom_date_format":"F j, Y","custom_time_format":"g:i a","show_icon":"custom","type":"terms","taxonomy":"category","_id":"2f08315"}],"space_between":{"unit":"px","size":25,"sizes":[]},"icon_align":"left","icon_color":"#797979","icon_size":{"unit":"px","size":21,"sizes":[]},"text_indent":{"unit":"px","size":6,"sizes":[]},"icon_typography_typography":"custom","icon_typography_font_family":"Manrope","icon_typography_font_size":{"unit":"px","size":14,"sizes":[]},"icon_typography_font_weight":"500","icon_typography_line_height":{"unit":"em","size":1,"sizes":[]},"_margin":{"unit":"px","top":"-2","right":"0","bottom":"-2","left":"-2","isLinked":false},"_padding":{"unit":"px","top":"35","right":"30","bottom":"0","left":"30","isLinked":false},"text_color":"#A2A2A2","icon_typography_text_transform":"capitalize"},"elements":[],"isInner":false,"widgetType":"post-info","elType":"widget"},{"id":"300f8653","settings":{"__dynamic__":{"title":"[elementor-tag id=\"\" name=\"post-title\" settings=\"%7B%22before%22%3A%22%22%2C%22after%22%3A%22%22%2C%22fallback%22%3A%22%22%7D\"]","link":"[elementor-tag id=\"e10263f\" name=\"post-url\" settings=\"%7B%7D\"]"},"title":"Add Your Heading Text Here","title_color":"#000000","typography_typography":"custom","typography_font_family":"Manrope","typography_font_size":{"unit":"px","size":22,"sizes":[]},"typography_font_weight":"700","typography_line_height":{"unit":"em","size":1.3,"sizes":[]},"_margin":{"unit":"px","top":"-5","right":"0","bottom":"-5","left":"0","isLinked":false},"_padding":{"unit":"px","top":"25","right":"30","bottom":"0","left":"30","isLinked":false},"header_size":"h3","typography_letter_spacing":{"unit":"px","size":-0.4,"sizes":[]}},"elements":[],"isInner":false,"widgetType":"theme-post-title","elType":"widget"},{"id":"751148ea","settings":{"text":"Read More","align":"left","typography_typography":"custom","typography_font_family":"Manrope","typography_font_size":{"unit":"px","size":14,"sizes":[]},"typography_font_weight":"600","typography_line_height":{"unit":"em","size":1,"sizes":[]},"button_text_color":"#000000","background_color":"#61CE7000","hover_color":"#FFFFFF","button_background_hover_color":"#000000","button_hover_border_color":"#000000","border_border":"solid","border_width":{"unit":"px","top":"1","right":"1","bottom":"1","left":"1","isLinked":true},"border_color":"#D3D3D3","border_radius":{"unit":"px","top":"0","right":"0","bottom":"0","left":"0","isLinked":true},"text_padding":{"unit":"px","top":"15","right":"25","bottom":"15","left":"25","isLinked":false},"_padding":{"unit":"px","top":"30","right":"0","bottom":"35","left":"30","isLinked":false},"__dynamic__":{"link":"[elementor-tag id=\"1b3524d\" name=\"post-url\" settings=\"%7B%7D\"]"},"typography_text_transform":"uppercase"},"elements":[],"isInner":false,"widgetType":"button","elType":"widget"},{"id":"b71f817","settings":{"icon_list":[{"selected_icon":{"value":"fas fa-calendar","library":"fa-solid"},"_id":"89979b4","date_format":"custom","custom_date_format":"d","custom_time_format":"g:i a","link":"","show_icon":"none"}],"icon_align":"center","text_indent":{"unit":"px","size":0,"sizes":[]},"text_color":"#FFFFFF","icon_typography_typography":"custom","icon_typography_font_family":"Manrope","icon_typography_font_size":{"unit":"px","size":18,"sizes":[]},"icon_typography_font_weight":"700","icon_typography_text_transform":"uppercase","icon_typography_line_height":{"unit":"em","size":1,"sizes":[]},"icon_typography_letter_spacing":{"unit":"px","size":-0.5,"sizes":[]},"_margin":{"unit":"%","top":"0","right":"0","bottom":"0","left":"80","isLinked":false},"_margin_tablet":{"unit":"%","top":"","right":"","bottom":"","left":"","isLinked":true},"_margin_mobile":{"unit":"%","top":"","right":"","bottom":"","left":"","isLinked":true},"_padding":{"unit":"px","top":"10","right":"0","bottom":"10","left":"0","isLinked":false},"_element_custom_width":{"unit":"px","size":70,"sizes":[]},"_position":"absolute","_offset_orientation_h":"end","_offset_x":{"unit":"px","size":"","sizes":[]},"_offset_x_end":{"unit":"px","size":20,"sizes":[]},"_offset_y":{"unit":"px","size":20,"sizes":[]},"_background_background":"classic","_background_color":"#C5C5C5"},"elements":[],"isInner":false,"widgetType":"post-info","elType":"widget"},{"id":"2cb0b4ef","settings":{"icon_list":[{"selected_icon":{"value":"fas fa-calendar","library":"fa-solid"},"_id":"89979b4","date_format":"custom","custom_date_format":"M","custom_time_format":"g:i a","link":"","show_icon":"none"}],"icon_align":"center","text_indent":{"unit":"px","size":0,"sizes":[]},"text_color":"#000000","icon_typography_typography":"custom","icon_typography_font_family":"Manrope","icon_typography_font_size":{"unit":"px","size":18,"sizes":[]},"icon_typography_font_weight":"700","icon_typography_text_transform":"uppercase","icon_typography_line_height":{"unit":"em","size":1,"sizes":[]},"icon_typography_letter_spacing":{"unit":"px","size":-0.5,"sizes":[]},"_margin":{"unit":"%","top":"0","right":"0","bottom":"0","left":"80","isLinked":false},"_margin_tablet":{"unit":"%","top":"","right":"","bottom":"","left":"","isLinked":true},"_margin_mobile":{"unit":"%","top":"","right":"","bottom":"","left":"","isLinked":true},"_padding":{"unit":"px","top":"8","right":"0","bottom":"8","left":"0","isLinked":false},"_element_custom_width":{"unit":"px","size":70,"sizes":[]},"_position":"absolute","_offset_orientation_h":"end","_offset_x":{"unit":"px","size":"","sizes":[]},"_offset_x_end":{"unit":"px","size":20,"sizes":[]},"_offset_y":{"unit":"px","size":54,"sizes":[]},"_background_background":"classic","_background_color":"#FFFFFF"},"elements":[],"isInner":false,"widgetType":"post-info","elType":"widget"},{"id":"a2f065","settings":{"icon_list":[{"selected_icon":{"value":"fas fa-calendar","library":"fa-solid"},"_id":"89979b4","date_format":"custom","custom_date_format":"d","custom_time_format":"g:i a","link":"","show_icon":"none"}],"icon_align":"center","text_indent":{"unit":"px","size":0,"sizes":[]},"text_color":"#FFFFFF","icon_typography_typography":"custom","icon_typography_font_family":"Manrope","icon_typography_font_size":{"unit":"px","size":18,"sizes":[]},"icon_typography_font_weight":"700","icon_typography_text_transform":"uppercase","icon_typography_line_height":{"unit":"em","size":1,"sizes":[]},"icon_typography_letter_spacing":{"unit":"px","size":-0.5,"sizes":[]},"_margin":{"unit":"%","top":"0","right":"0","bottom":"0","left":"80","isLinked":false},"_margin_tablet":{"unit":"%","top":"","right":"","bottom":"","left":"","isLinked":true},"_margin_mobile":{"unit":"%","top":"","right":"","bottom":"","left":"","isLinked":true},"_padding":{"unit":"px","top":"8","right":"0","bottom":"8","left":"0","isLinked":false},"_element_custom_width":{"unit":"px","size":70,"sizes":[]},"_position":"absolute","_offset_orientation_h":"end","_offset_x":{"unit":"px","size":"","sizes":[]},"_offset_x_end":{"unit":"px","size":20,"sizes":[]},"_offset_y":{"unit":"px","size":20,"sizes":[]},"_background_background":"classic","_background_color":"#4D4D4D"},"elements":[],"isInner":false,"widgetType":"post-info","elType":"widget"}],"isInner":true,"elType":"column"}],"isInner":true,"elType":"section"}],"isInner":false,"elType":"column"}],"isInner":false,"elType":"section"}],"page_settings":[],"version":"0.4","title":"1938-loop","type":"loop-item"}