{"content":[{"id":"561ed06d","settings":{"content_width":{"unit":"px","size":1290,"sizes":[]},"gap":"no","background_background":"classic","background_color":"#F5F5F5","padding":{"unit":"px","top":"120","right":"40","bottom":"120","left":"40","isLinked":false},"padding_tablet":{"unit":"px","top":"80","right":"40","bottom":"80","left":"40","isLinked":false},"padding_mobile":{"unit":"px","top":"60","right":"20","bottom":"60","left":"20","isLinked":false},"_title":"Blank Sections"},"elements":[{"id":"4332db17","settings":{"_column_size":100,"_inline_size":null},"elements":[{"id":"84d1d43","settings":{"content_width":{"unit":"px","size":1290,"sizes":[]},"gap":"no","background_background":"classic"},"elements":[{"id":"5d21b1bf","settings":{"_column_size":100,"_inline_size":null,"space_between_widgets":0},"elements":[{"id":"2d1846dd","settings":{"title":"Porro est dolorem ipsum dolor sit amet consec tetur adipisci velit sed numsuam modi.","header_size":"h1","title_color":"#000000","typography_typography":"custom","typography_font_family":"Manrope","typography_font_size":{"unit":"px","size":52,"sizes":[]},"typography_font_weight":"700","typography_line_height":{"unit":"em","size":1.1,"sizes":[]},"typography_letter_spacing":{"unit":"px","size":-1.5,"sizes":[]},"typography_font_size_tablet":{"unit":"px","size":35,"sizes":[]},"typography_font_size_mobile":{"unit":"px","size":32,"sizes":[]},"align":"left","_margin":{"unit":"px","top":"-10","right":"0","bottom":"-9","left":"-4","isLinked":false},"typography_line_height_mobile":{"unit":"em","size":1.2,"sizes":[]},"_margin_tablet":{"unit":"px","top":"-7","right":"0","bottom":"0","left":"-2","isLinked":false},"_margin_mobile":{"unit":"px","top":"-8","right":"0","bottom":"0","left":"-2","isLinked":false},"_element_width":"initial","_element_custom_width":{"unit":"px","size":784,"sizes":[]},"_element_custom_width_tablet":{"unit":"px","size":533,"sizes":[]}},"elements":[],"isInner":false,"widgetType":"heading","elType":"widget"}],"isInner":true,"elType":"column"}],"isInner":true,"elType":"section"},{"id":"4561b5f","settings":{"content_width":{"unit":"px","size":1290,"sizes":[]},"gap":"no","background_background":"classic"},"elements":[{"id":"484ab729","settings":{"_column_size":100,"_inline_size":null,"space_between_widgets":0,"align":"flex-end","padding":{"unit":"px","top":"24","right":"0","bottom":"40","left":"0","isLinked":false},"padding_tablet":{"unit":"px","top":"30","right":"0","bottom":"25","left":"180","isLinked":false},"padding_mobile":{"unit":"px","top":"21","right":"0","bottom":"20","left":"0","isLinked":false}},"elements":[{"id":"2d831582","settings":{"editor":"<p>Lorem ipsum dolor sit amet consec tetur adipis cing elit do eiusmod tempor ut labore et magna aliqua. Ut enim ad minim veniam nostrud exercitation ullamco laboris nisi ut commodo aute irure dolor in repreh enderit esse dolor eu fugiat nulla pariatur. Excepteur sint proident sunt in culpa officia deserunt mollit anim est laborum. Sed ut unde omnis iste natus sit volur tatem accus antium laudan tium totam rem aperiam eaque ipsa ab illo inventore veritatis et architecto beatae vitae dicta sunt\u00a0 enim quia sit asper natur sed magni dolores nostrum exercita tionem ullam corporis.<\/p>","text_columns":"1","align":"left","text_color":"#9F9F9F","typography_typography":"custom","typography_font_family":"Manrope","typography_font_size":{"unit":"px","size":15,"sizes":[]},"typography_font_weight":"500","typography_line_height":{"unit":"em","size":1.8,"sizes":[]},"typography_font_size_tablet":{"unit":"px","size":14,"sizes":[]},"typography_font_size_mobile":{"unit":"px","size":14,"sizes":[]},"_element_width":"initial","_element_custom_width":{"unit":"px","size":717,"sizes":[]}},"elements":[],"isInner":false,"widgetType":"text-editor","elType":"widget"}],"isInner":true,"elType":"column"}],"isInner":true,"elType":"section"},{"id":"3d69765f","settings":{"content_width":{"unit":"px","size":1290,"sizes":[]},"gap":"no","structure":"20","background_background":"classic"},"elements":[{"id":"126e60a7","settings":{"_column_size":50,"_inline_size":null,"space_between_widgets":0,"_inline_size_mobile":50,"margin":{"unit":"px","top":"0","right":"20","bottom":"0","left":"0","isLinked":false},"margin_mobile":{"unit":"px","top":"0","right":"10","bottom":"0","left":"0","isLinked":false}},"elements":[{"id":"5bd15227","settings":{"image":{"url":"https:\/\/blocks.elementorking.com\/wp-content\/uploads\/2023\/06\/l61.png","id":2695,"size":"","alt":"","source":"library"},"image_border_radius":{"unit":"px","top":"10","right":"10","bottom":"10","left":"10","isLinked":true}},"elements":[],"isInner":false,"widgetType":"image","elType":"widget"}],"isInner":true,"elType":"column"},{"id":"5b36049f","settings":{"_column_size":50,"_inline_size":null,"space_between_widgets":0,"_inline_size_mobile":50,"margin":{"unit":"px","top":"0","right":"0","bottom":"0","left":"20","isLinked":false},"margin_mobile":{"unit":"px","top":"0","right":"0","bottom":"0","left":"10","isLinked":false}},"elements":[{"id":"3ff6d687","settings":{"image":{"url":"https:\/\/blocks.elementorking.com\/wp-content\/uploads\/2023\/06\/l61.png","id":2695,"size":"","alt":"","source":"library"},"image_border_radius":{"unit":"px","top":"10","right":"10","bottom":"10","left":"10","isLinked":true}},"elements":[],"isInner":false,"widgetType":"image","elType":"widget"}],"isInner":true,"elType":"column"}],"isInner":true,"elType":"section"}],"isInner":false,"elType":"column"}],"isInner":false,"elType":"section"}],"page_settings":{"hide_title":"yes"},"version":"0.4","title":"L1209","type":"section"}