{"content":[{"id":"776a6e17","settings":{"content_width":{"unit":"px","size":1310,"sizes":[]},"gap":"no","structure":"20","background_background":"classic","background_color":"#F5F5F5","padding":{"unit":"px","top":"120","right":"120","bottom":"120","left":"120","isLinked":true},"padding_tablet":{"unit":"px","top":"80","right":"40","bottom":"80","left":"40","isLinked":false},"padding_mobile":{"unit":"px","top":"60","right":"20","bottom":"60","left":"20","isLinked":false}},"elements":[{"id":"23c56da","settings":{"_column_size":50,"_inline_size":25,"space_between_widgets":0},"elements":[{"id":"34db9095","settings":{"gap":"no","padding":{"unit":"custom","top":"0","right":"0","bottom":"0","left":"0","isLinked":false},"padding_tablet":{"unit":"custom","top":"","right":"","bottom":"","left":"","isLinked":true},"padding_mobile":{"unit":"custom","top":"","right":"","bottom":"","left":"","isLinked":true}},"elements":[{"id":"1459e418","settings":{"_column_size":100,"_inline_size":100,"space_between_widgets":0,"padding":{"unit":"custom","top":"0","right":"1vh","bottom":"0","left":"1vh","isLinked":false},"padding_tablet":{"unit":"custom","top":"","right":"","bottom":"","left":"","isLinked":true},"padding_mobile":{"unit":"custom","top":"0","right":"0","bottom":"0","left":"0","isLinked":false}},"elements":[{"id":"79c0f466","settings":{"image":{"url":"https:\/\/blocks.elementorking.com\/wp-content\/uploads\/2023\/06\/l28.png","id":2138,"size":"","alt":"","source":"library"},"image_size":"full","align":"center","link_to":"file","open_lightbox":"yes","width":{"unit":"px","size":1000,"sizes":[]},"width_tablet":{"unit":"px","size":1000,"sizes":[]},"width_mobile":{"unit":"px","size":1000,"sizes":[]},"height":{"unit":"vh","size":30,"sizes":[]},"height_tablet":{"unit":"vh","size":19,"sizes":[]},"height_mobile":{"unit":"vh","size":25,"sizes":[]},"object-fit":"cover","opacity_hover":{"unit":"px","size":0.9,"sizes":[]},"_padding":{"unit":"custom","top":"0","right":"0","bottom":"0","left":"0","isLinked":false},"_padding_tablet":{"unit":"custom","top":"","right":"","bottom":"","left":"","isLinked":true},"_padding_mobile":{"unit":"px","top":"0","right":"0","bottom":"0","left":"0","isLinked":false}},"elements":[],"isInner":false,"widgetType":"image","elType":"widget"},{"id":"29f3d96c","settings":{"image":{"url":"https:\/\/blocks.elementorking.com\/wp-content\/uploads\/2023\/06\/l28.png","id":2138,"size":"","alt":"","source":"library"},"image_size":"full","align":"center","link_to":"file","open_lightbox":"yes","width":{"unit":"px","size":1000,"sizes":[]},"width_tablet":{"unit":"px","size":1000,"sizes":[]},"width_mobile":{"unit":"px","size":1000,"sizes":[]},"height":{"unit":"vh","size":62,"sizes":[]},"height_tablet":{"unit":"vh","size":38,"sizes":[]},"height_mobile":{"unit":"vh","size":60,"sizes":[]},"object-fit":"cover","opacity_hover":{"unit":"px","size":0.9,"sizes":[]},"_padding":{"unit":"custom","top":"2vh","right":"0","bottom":"0","left":"0","isLinked":false},"_padding_tablet":{"unit":"custom","top":"","right":"","bottom":"","left":"","isLinked":true},"_padding_mobile":{"unit":"px","top":"10","right":"0","bottom":"0","left":"0","isLinked":false}},"elements":[],"isInner":false,"widgetType":"image","elType":"widget"}],"isInner":true,"elType":"column"}],"isInner":true,"elType":"section"}],"isInner":false,"elType":"column"},{"id":"1ead7e09","settings":{"_column_size":50,"_inline_size":75,"space_between_widgets":0},"elements":[{"id":"5ec0e354","settings":{"gap":"no","structure":"20","padding":{"unit":"custom","top":"0","right":"0","bottom":"0","left":"0","isLinked":false},"padding_tablet":{"unit":"custom","top":"","right":"","bottom":"","left":"","isLinked":true},"padding_mobile":{"unit":"custom","top":"","right":"","bottom":"","left":"","isLinked":true}},"elements":[{"id":"48cbc2c5","settings":{"_column_size":50,"_inline_size":66.6,"space_between_widgets":0,"padding":{"unit":"custom","top":"0","right":"1vh","bottom":"0","left":"1vh","isLinked":false},"padding_tablet":{"unit":"custom","top":"","right":"","bottom":"","left":"","isLinked":true},"padding_mobile":{"unit":"custom","top":"0","right":"0","bottom":"0","left":"0","isLinked":false}},"elements":[{"id":"53dabc67","settings":{"image":{"url":"https:\/\/blocks.elementorking.com\/wp-content\/uploads\/2023\/06\/l28.png","id":2138,"size":"","alt":"","source":"library"},"image_size":"full","align":"center","link_to":"file","open_lightbox":"yes","width":{"unit":"px","size":1000,"sizes":[]},"width_tablet":{"unit":"px","size":1000,"sizes":[]},"width_mobile":{"unit":"px","size":1000,"sizes":[]},"height":{"unit":"vh","size":62,"sizes":[]},"height_tablet":{"unit":"vh","size":40,"sizes":[]},"height_mobile":{"unit":"vh","size":30,"sizes":[]},"object-fit":"cover","opacity_hover":{"unit":"px","size":0.9,"sizes":[]},"_padding":{"unit":"custom","top":"0","right":"0","bottom":"0","left":"0","isLinked":false},"_padding_tablet":{"unit":"custom","top":"","right":"","bottom":"","left":"","isLinked":true},"_padding_mobile":{"unit":"px","top":"10","right":"0","bottom":"0","left":"0","isLinked":false}},"elements":[],"isInner":false,"widgetType":"image","elType":"widget"}],"isInner":true,"elType":"column"},{"id":"50ed2321","settings":{"_column_size":50,"_inline_size":33.4,"space_between_widgets":0,"padding":{"unit":"custom","top":"0","right":"1vh","bottom":"0","left":"1vh","isLinked":false},"padding_tablet":{"unit":"custom","top":"","right":"","bottom":"","left":"","isLinked":true},"padding_mobile":{"unit":"custom","top":"0","right":"0","bottom":"0","left":"0","isLinked":false}},"elements":[{"id":"7f471a0d","settings":{"image":{"url":"https:\/\/blocks.elementorking.com\/wp-content\/uploads\/2023\/06\/l28.png","id":2138,"size":"","alt":"","source":"library"},"image_size":"full","align":"center","link_to":"file","open_lightbox":"yes","width":{"unit":"px","size":1000,"sizes":[]},"width_tablet":{"unit":"px","size":1000,"sizes":[]},"width_mobile":{"unit":"px","size":1000,"sizes":[]},"height":{"unit":"vh","size":30,"sizes":[]},"height_tablet":{"unit":"vh","size":19,"sizes":[]},"height_mobile":{"unit":"vh","size":25,"sizes":[]},"object-fit":"cover","opacity_hover":{"unit":"px","size":0.9,"sizes":[]},"_padding":{"unit":"custom","top":"0","right":"0","bottom":"0","left":"0","isLinked":false},"_padding_tablet":{"unit":"custom","top":"","right":"","bottom":"","left":"","isLinked":true},"_padding_mobile":{"unit":"px","top":"10","right":"0","bottom":"0","left":"0","isLinked":false}},"elements":[],"isInner":false,"widgetType":"image","elType":"widget"},{"id":"4e187973","settings":{"image":{"url":"https:\/\/blocks.elementorking.com\/wp-content\/uploads\/2023\/06\/l28.png","id":2138,"size":"","alt":"","source":"library"},"image_size":"full","align":"center","link_to":"file","open_lightbox":"yes","width":{"unit":"px","size":1000,"sizes":[]},"width_tablet":{"unit":"px","size":1000,"sizes":[]},"width_mobile":{"unit":"px","size":1000,"sizes":[]},"height":{"unit":"vh","size":30,"sizes":[]},"height_tablet":{"unit":"vh","size":19,"sizes":[]},"height_mobile":{"unit":"vh","size":25,"sizes":[]},"object-fit":"cover","opacity_hover":{"unit":"px","size":0.9,"sizes":[]},"_padding":{"unit":"custom","top":"2vh","right":"0","bottom":"0","left":"0","isLinked":false},"_padding_tablet":{"unit":"custom","top":"","right":"","bottom":"","left":"","isLinked":true},"_padding_mobile":{"unit":"px","top":"10","right":"0","bottom":"0","left":"0","isLinked":false}},"elements":[],"isInner":false,"widgetType":"image","elType":"widget"}],"isInner":true,"elType":"column"}],"isInner":true,"elType":"section"},{"id":"6b3f0c15","settings":{"gap":"no","structure":"20","padding":{"unit":"custom","top":"2vh","right":"0","bottom":"0","left":"0","isLinked":false},"padding_tablet":{"unit":"custom","top":"","right":"","bottom":"","left":"","isLinked":true},"padding_mobile":{"unit":"custom","top":"0","right":"0","bottom":"0","left":"0","isLinked":false}},"elements":[{"id":"50e7530b","settings":{"_column_size":50,"_inline_size":33.4,"space_between_widgets":0,"padding":{"unit":"custom","top":"0","right":"1vh","bottom":"0","left":"1vh","isLinked":false},"padding_tablet":{"unit":"custom","top":"","right":"","bottom":"","left":"","isLinked":true},"padding_mobile":{"unit":"custom","top":"0","right":"0","bottom":"0","left":"0","isLinked":false}},"elements":[{"id":"161ae22d","settings":{"image":{"url":"https:\/\/blocks.elementorking.com\/wp-content\/uploads\/2023\/06\/l28.png","id":2138,"size":"","alt":"","source":"library"},"image_size":"full","align":"center","link_to":"file","open_lightbox":"yes","width":{"unit":"px","size":1000,"sizes":[]},"width_tablet":{"unit":"px","size":1000,"sizes":[]},"width_mobile":{"unit":"px","size":1000,"sizes":[]},"height":{"unit":"vh","size":30,"sizes":[]},"height_tablet":{"unit":"vh","size":17,"sizes":[]},"height_mobile":{"unit":"vh","size":25,"sizes":[]},"object-fit":"cover","opacity_hover":{"unit":"px","size":0.9,"sizes":[]},"_padding":{"unit":"custom","top":"0","right":"0","bottom":"0","left":"0","isLinked":false},"_padding_tablet":{"unit":"custom","top":"","right":"","bottom":"","left":"","isLinked":true},"_padding_mobile":{"unit":"px","top":"10","right":"0","bottom":"0","left":"0","isLinked":false}},"elements":[],"isInner":false,"widgetType":"image","elType":"widget"}],"isInner":true,"elType":"column"},{"id":"435fa8b2","settings":{"_column_size":50,"_inline_size":66.6,"space_between_widgets":0,"padding":{"unit":"custom","top":"0","right":"1vh","bottom":"0","left":"1vh","isLinked":false},"padding_tablet":{"unit":"custom","top":"","right":"","bottom":"","left":"","isLinked":true},"padding_mobile":{"unit":"custom","top":"0","right":"0","bottom":"0","left":"0","isLinked":false}},"elements":[{"id":"4b471a4e","settings":{"image":{"url":"https:\/\/blocks.elementorking.com\/wp-content\/uploads\/2023\/06\/l28.png","id":2138,"size":"","alt":"","source":"library"},"image_size":"full","align":"center","link_to":"file","open_lightbox":"yes","width":{"unit":"px","size":1000,"sizes":[]},"width_tablet":{"unit":"px","size":1000,"sizes":[]},"width_mobile":{"unit":"px","size":1000,"sizes":[]},"height":{"unit":"vh","size":30,"sizes":[]},"height_tablet":{"unit":"vh","size":17,"sizes":[]},"height_mobile":{"unit":"vh","size":19,"sizes":[]},"object-fit":"cover","opacity_hover":{"unit":"px","size":0.9,"sizes":[]},"_padding":{"unit":"custom","top":"0","right":"0","bottom":"0","left":"0","isLinked":false},"_padding_tablet":{"unit":"custom","top":"","right":"","bottom":"","left":"","isLinked":true},"_padding_mobile":{"unit":"px","top":"10","right":"0","bottom":"0","left":"0","isLinked":false}},"elements":[],"isInner":false,"widgetType":"image","elType":"widget"}],"isInner":true,"elType":"column"}],"isInner":true,"elType":"section"}],"isInner":false,"elType":"column"}],"isInner":false,"elType":"section"}],"page_settings":{"hide_title":"yes"},"version":"0.4","title":"L215","type":"section"}