{"content":[{"id":"353b2f5","settings":{"content_width":{"unit":"px","size":1290,"sizes":[]},"gap":"no","background_background":"classic","background_color":"#F5F5F5","padding":{"unit":"px","top":"102","right":"40","bottom":"106","left":"40","isLinked":false},"padding_tablet":{"unit":"px","top":"80","right":"40","bottom":"80","left":"40","isLinked":false},"padding_mobile":{"unit":"px","top":"60","right":"20","bottom":"60","left":"20","isLinked":false},"_title":"Blank Sections"},"elements":[{"id":"6863dba7","settings":{"_column_size":100,"_inline_size":null},"elements":[{"id":"104b9f0d","settings":{"content_width":{"unit":"px","size":1290,"sizes":[]},"gap":"no","structure":"20","background_background":"classic","padding_mobile":{"unit":"px","top":"0","right":"0","bottom":"0","left":"0","isLinked":false}},"elements":[{"id":"25773fbf","settings":{"_column_size":50,"_inline_size":30,"space_between_widgets":0,"padding_mobile":{"unit":"px","top":"0","right":"0","bottom":"30","left":"0","isLinked":false}},"elements":[{"id":"20dc5d10","settings":{"title":"REFERENCES","header_size":"h5","title_color":"#000000","typography_typography":"custom","typography_font_family":"Manrope","typography_font_size":{"unit":"px","size":25,"sizes":[]},"typography_font_weight":"700","typography_line_height":{"unit":"em","size":1,"sizes":[]},"typography_letter_spacing":{"unit":"px","size":-0.6,"sizes":[]},"typography_font_size_tablet":{"unit":"px","size":20,"sizes":[]},"typography_font_size_mobile":{"unit":"px","size":20,"sizes":[]},"_margin":{"unit":"px","top":"15","right":"0","bottom":"0","left":"0","isLinked":false},"_margin_mobile":{"unit":"px","top":"-3","right":"0","bottom":"0","left":"0","isLinked":false}},"elements":[],"isInner":false,"widgetType":"heading","elType":"widget"}],"isInner":true,"elType":"column"},{"id":"16c132e0","settings":{"_column_size":50,"_inline_size":70,"space_between_widgets":0},"elements":[{"id":"3edaccdd","settings":{"structure":"40"},"elements":[{"id":"19aa1383","settings":{"_column_size":25,"_inline_size":null,"_inline_size_mobile":50,"space_between_widgets":0,"margin_mobile":{"unit":"px","top":"0","right":"0","bottom":"0","left":"0","isLinked":false},"padding_mobile":{"unit":"px","top":"0","right":"0","bottom":"0","left":"0","isLinked":false}},"elements":[{"id":"6d44eae4","settings":{"image":{"url":"https:\/\/blocks.elementorking.com\/wp-content\/uploads\/2023\/06\/logos-light-6.png","id":1500,"size":"","alt":"","source":"library"},"align":"right","align_mobile":"left","width":{"unit":"px","size":135,"sizes":[]},"width_tablet":{"unit":"px","size":"","sizes":[]},"width_mobile":{"unit":"px","size":"","sizes":[]},"_padding_mobile":{"unit":"px","top":"0","right":"0","bottom":"0","left":"0","isLinked":false}},"elements":[],"isInner":false,"widgetType":"image","elType":"widget"},{"id":"6fa8b863","settings":{"image":{"url":"https:\/\/blocks.elementorking.com\/wp-content\/uploads\/2023\/06\/logos-light-3.png","id":1497,"size":"","alt":"","source":"library"},"align":"right","align_mobile":"left","width":{"unit":"px","size":135,"sizes":[]},"width_tablet":{"unit":"px","size":"","sizes":[]},"width_mobile":{"unit":"px","size":"","sizes":[]},"_margin":{"unit":"px","top":"60","right":"0","bottom":"0","left":"0","isLinked":false},"_margin_mobile":{"unit":"px","top":"0","right":"0","bottom":"0","left":"0","isLinked":false}},"elements":[],"isInner":false,"widgetType":"image","elType":"widget"}],"isInner":true,"elType":"column"},{"id":"4a76e580","settings":{"_column_size":25,"_inline_size":null,"_inline_size_mobile":50,"space_between_widgets":0,"padding_mobile":{"unit":"px","top":"0","right":"0","bottom":"0","left":"0","isLinked":false}},"elements":[{"id":"43245206","settings":{"image":{"url":"https:\/\/blocks.elementorking.com\/wp-content\/uploads\/2023\/06\/logos-light-5.png","id":1499,"size":"","alt":"","source":"library"},"align":"right","align_mobile":"left","width":{"unit":"px","size":135,"sizes":[]},"width_tablet":{"unit":"px","size":"","sizes":[]},"width_mobile":{"unit":"px","size":"","sizes":[]}},"elements":[],"isInner":false,"widgetType":"image","elType":"widget"},{"id":"79a3f975","settings":{"image":{"url":"https:\/\/blocks.elementorking.com\/wp-content\/uploads\/2023\/06\/logos-light-2.png","id":1496,"size":"","alt":"","source":"library"},"align":"right","align_mobile":"left","width":{"unit":"px","size":135,"sizes":[]},"width_tablet":{"unit":"px","size":"","sizes":[]},"width_mobile":{"unit":"px","size":"","sizes":[]},"_margin":{"unit":"px","top":"60","right":"0","bottom":"0","left":"0","isLinked":false},"_margin_mobile":{"unit":"px","top":"0","right":"0","bottom":"0","left":"0","isLinked":false}},"elements":[],"isInner":false,"widgetType":"image","elType":"widget"}],"isInner":true,"elType":"column"},{"id":"1b0bc296","settings":{"_column_size":25,"_inline_size":null,"_inline_size_mobile":50,"space_between_widgets":0,"padding_mobile":{"unit":"px","top":"0","right":"0","bottom":"0","left":"0","isLinked":true}},"elements":[{"id":"6130833f","settings":{"image":{"url":"https:\/\/blocks.elementorking.com\/wp-content\/uploads\/2023\/06\/logos-light-3.png","id":1497,"size":"","alt":"","source":"library"},"align":"right","align_mobile":"left","width":{"unit":"px","size":135,"sizes":[]},"width_tablet":{"unit":"px","size":"","sizes":[]},"width_mobile":{"unit":"px","size":"","sizes":[]}},"elements":[],"isInner":false,"widgetType":"image","elType":"widget"},{"id":"8534760","settings":{"image":{"url":"https:\/\/blocks.elementorking.com\/wp-content\/uploads\/2023\/06\/logos-light-6.png","id":1500,"size":"","alt":"","source":"library"},"align":"right","align_mobile":"left","width":{"unit":"px","size":135,"sizes":[]},"width_tablet":{"unit":"px","size":"","sizes":[]},"width_mobile":{"unit":"px","size":"","sizes":[]},"_margin":{"unit":"px","top":"60","right":"0","bottom":"0","left":"0","isLinked":false},"_margin_mobile":{"unit":"px","top":"0","right":"0","bottom":"0","left":"0","isLinked":false}},"elements":[],"isInner":false,"widgetType":"image","elType":"widget"}],"isInner":true,"elType":"column"},{"id":"3a2f3382","settings":{"_column_size":25,"_inline_size":null,"_inline_size_mobile":50,"space_between_widgets":0,"padding_mobile":{"unit":"px","top":"0","right":"0","bottom":"0","left":"0","isLinked":false}},"elements":[{"id":"8e8368b","settings":{"image":{"url":"https:\/\/blocks.elementorking.com\/wp-content\/uploads\/2023\/06\/logos-light-4.png","id":1498,"size":"","alt":"","source":"library"},"align":"right","align_mobile":"left","width":{"unit":"px","size":135,"sizes":[]},"width_tablet":{"unit":"px","size":"","sizes":[]},"width_mobile":{"unit":"px","size":"","sizes":[]}},"elements":[],"isInner":false,"widgetType":"image","elType":"widget"},{"id":"7f10817c","settings":{"image":{"url":"https:\/\/blocks.elementorking.com\/wp-content\/uploads\/2023\/06\/logos-light-5.png","id":1499,"size":"","alt":"","source":"library"},"align":"right","align_mobile":"left","width":{"unit":"px","size":135,"sizes":[]},"width_tablet":{"unit":"px","size":"","sizes":[]},"width_mobile":{"unit":"px","size":"","sizes":[]},"_margin":{"unit":"px","top":"60","right":"0","bottom":"0","left":"0","isLinked":false},"_margin_mobile":{"unit":"px","top":"0","right":"0","bottom":"0","left":"0","isLinked":false}},"elements":[],"isInner":false,"widgetType":"image","elType":"widget"}],"isInner":true,"elType":"column"}],"isInner":true,"elType":"section"}],"isInner":true,"elType":"column"}],"isInner":true,"elType":"section"}],"isInner":false,"elType":"column"}],"isInner":false,"elType":"section"}],"page_settings":{"hide_title":"yes"},"version":"0.4","title":"L756","type":"section"}